{
  "2022-08-10": {
    "stocks": [
      {
        "symbol": "PAGEIND",
        "shares": 0,
        "amount": 0.0
      },
      {
        "symbol": "HAL",
        "shares": -22,
        "amount": -23851.300000000003
      },
      {
        "symbol": "ATGL",
        "shares": -7,
        "amount": -23459.8
      },
      {
        "symbol": "ABB",
        "shares": -7,
        "amount": -19392.8
      },
      {
        "symbol": "ADANIGREEN",
        "shares": -8,
        "amount": -17319.6
      },
      {
        "symbol": "AUBANK",
        "shares": -26,
        "amount": -16773.899999999998
      },
      {
        "symbol": "CONCOR",
        "shares": -24,
        "amount": -16570.800000000003
      },
      {
        "symbol": "FORTIS",
        "shares": -57,
        "amount": -15236.1
      },
      {
        "symbol": "PRESTIGE",
        "shares": -33,
        "amount": -14373.15
      },
      {
        "symbol": "TATACOMM",
        "shares": -13,
        "amount": -14086.8
      },
      {
        "symbol": "ADANIPOWER",
        "shares": -41,
        "amount": -13929.75
      },
      {
        "symbol": "OIL",
        "shares": -69,
        "amount": -12896.1
      },
      {
        "symbol": "JINDALSTEL",
        "shares": -31,
        "amount": -12294.6
      },
      {
        "symbol": "ADANIENT",
        "shares": -3,
        "amount": -8481.599999999999
      },
      {
        "symbol": "APOLLOHOSP",
        "shares": 3,
        "amount": 13551.449999999999
      },
      {
        "symbol": "ADANIENSOL",
        "shares": 4,
        "amount": 13744.6
      },
      {
        "symbol": "POLYCAB",
        "shares": 6,
        "amount": 14526.900000000001
      },
      {
        "symbol": "APLAPOLLO",
        "shares": 15,
        "amount": 15755.249999999998
      },
      {
        "symbol": "TATACHEM",
        "shares": 15,
        "amount": 16112.250000000002
      },
      {
        "symbol": "COROMANDEL",
        "shares": 15,
        "amount": 16143.0
      },
      {
        "symbol": "IRCTC",
        "shares": 24,
        "amount": 16155.599999999999
      },
      {
        "symbol": "HINDALCO",
        "shares": 37,
        "amount": 16283.7
      },
      {
        "symbol": "IGL",
        "shares": 43,
        "amount": 16331.4
      },
      {
        "symbol": "JSWENERGY",
        "shares": 51,
        "amount": 16381.199999999999
      },
      {
        "symbol": "BEL",
        "shares": 173,
        "amount": 16573.399999999998
      },
      {
        "symbol": "NMDC",
        "shares": 203,
        "amount": 16613.52
      },
      {
        "symbol": "IDFCFIRSTB",
        "shares": 372,
        "amount": 16665.6
      }
    ],
    "capital_incurred": -3828.4299999999894,
    "start_date": "2022-03-31",
    "end_date": "2022-08-10"
  },
  "2022-12-22": {
    "stocks": [
      {
        "symbol": "APOLLOHOSP",
        "shares": 0,
        "amount": 0.0
      },
      {
        "symbol": "SHREECEM",
        "shares": 0,
        "amount": 0.0
      },
      {
        "symbol": "NMDC",
        "shares": -203,
        "amount": -23730.7
      },
      {
        "symbol": "IDFCFIRSTB",
        "shares": -372,
        "amount": -21185.4
      },
      {
        "symbol": "ADANIENT",
        "shares": -5,
        "amount": -19342.75
      },
      {
        "symbol": "IGL",
        "shares": -43,
        "amount": -18251.35
      },
      {
        "symbol": "BEL",
        "shares": -173,
        "amount": -16997.25
      },
      {
        "symbol": "HINDALCO",
        "shares": -37,
        "amount": -16853.5
      },
      {
        "symbol": "APLAPOLLO",
        "shares": -15,
        "amount": -15926.25
      },
      {
        "symbol": "POLYCAB",
        "shares": -6,
        "amount": -15702.300000000001
      },
      {
        "symbol": "IRCTC",
        "shares": -24,
        "amount": -15382.800000000001
      },
      {
        "symbol": "TATACHEM",
        "shares": -15,
        "amount": -14103.75
      },
      {
        "symbol": "JSWENERGY",
        "shares": -51,
        "amount": -13772.550000000001
      },
      {
        "symbol": "ADANIPOWER",
        "shares": -49,
        "amount": -13524.0
      },
      {
        "symbol": "COROMANDEL",
        "shares": -15,
        "amount": -13380.75
      },
      {
        "symbol": "ADANIENSOL",
        "shares": -4,
        "amount": -10072.0
      },
      {
        "symbol": "TIINDIA",
        "shares": 5,
        "amount": 14628.75
      },
      {
        "symbol": "BALKRISIND",
        "shares": 7,
        "amount": 15068.550000000001
      },
      {
        "symbol": "ALKEM",
        "shares": 5,
        "amount": 15431.75
      },
      {
        "symbol": "MPHASIS",
        "shares": 8,
        "amount": 15913.2
      },
      {
        "symbol": "GODREJCP",
        "shares": 18,
        "amount": 16044.300000000001
      },
      {
        "symbol": "LUPIN",
        "shares": 21,
        "amount": 16092.3
      },
      {
        "symbol": "ICICIGI",
        "shares": 13,
        "amount": 16116.75
      },
      {
        "symbol": "KPITTECH",
        "shares": 23,
        "amount": 16354.15
      },
      {
        "symbol": "MAXHEALTH",
        "shares": 37,
        "amount": 16546.399999999998
      },
      {
        "symbol": "JUBLFOOD",
        "shares": 31,
        "amount": 16547.8
      },
      {
        "symbol": "VBL",
        "shares": 24,
        "amount": 16566.72
      },
      {
        "symbol": "CROMPTON",
        "shares": 47,
        "amount": 16600.399999999998
      },
      {
        "symbol": "RECLTD",
        "shares": 148,
        "amount": 16650.0
      }
    ],
    "capital_incurred": -19664.280000000013,
    "start_date": "2022-08-10",
    "end_date": "2022-12-22"
  },
  "2023-05-09": {
    "stocks": [
      {
        "symbol": "SHREECEM",
        "shares": 0,
        "amount": 0.0
      },
      {
        "symbol": "KPITTECH",
        "shares": -23,
        "amount": -20252.649999999998
      },
      {
        "symbol": "RECLTD",
        "shares": -148,
        "amount": -19528.6
      },
      {
        "symbol": "MAXHEALTH",
        "shares": -37,
        "amount": -17808.100000000002
      },
      {
        "symbol": "GODREJCP",
        "shares": -18,
        "amount": -17123.399999999998
      },
      {
        "symbol": "BALKRISIND",
        "shares": -7,
        "amount": -15104.25
      },
      {
        "symbol": "MPHASIS",
        "shares": -8,
        "amount": -14881.6
      },
      {
        "symbol": "JUBLFOOD",
        "shares": -31,
        "amount": -14371.6
      },
      {
        "symbol": "ICICIGI",
        "shares": -13,
        "amount": -14281.15
      },
      {
        "symbol": "APOLLOHOSP",
        "shares": -3,
        "amount": -13779.150000000001
      },
      {
        "symbol": "CROMPTON",
        "shares": -47,
        "amount": -12029.65
      },
      {
        "symbol": "ALKEM",
        "shares": -1,
        "amount": -3618.05
      },
      {
        "symbol": "VBL",
        "shares": -2,
        "amount": -1505.46
      },
      {
        "symbol": "LUPIN",
        "shares": 1,
        "amount": 745.55
      },
      {
        "symbol": "TIINDIA",
        "shares": 1,
        "amount": 2721.25
      },
      {
        "symbol": "DIVISLAB",
        "shares": 4,
        "amount": 13532.8
      },
      {
        "symbol": "TATAELXSI",
        "shares": 2,
        "amount": 13983.9
      },
      {
        "symbol": "TATACOMM",
        "shares": 12,
        "amount": 15596.400000000001
      },
      {
        "symbol": "LODHA",
        "shares": 34,
        "amount": 16314.22
      },
      {
        "symbol": "LAURUSLABS",
        "shares": 49,
        "amount": 16373.349999999999
      },
      {
        "symbol": "APOLLOTYRE",
        "shares": 43,
        "amount": 16408.8
      },
      {
        "symbol": "INDHOTEL",
        "shares": 44,
        "amount": 16467.0
      },
      {
        "symbol": "FACT",
        "shares": 52,
        "amount": 16538.600000000002
      },
      {
        "symbol": "DEVYANI",
        "shares": 93,
        "amount": 16567.95
      },
      {
        "symbol": "ADANIPOWER",
        "shares": 69,
        "amount": 16580.7
      },
      {
        "symbol": "CGPOWER",
        "shares": 52,
        "amount": 16666.0
      }
    ],
    "capital_incurred": 14212.860000000011,
    "start_date": "2022-12-22",
    "end_date": "2023-05-09"
  },
  "2023-09-15": {
    "stocks": [
      {
        "symbol": "LODHA",
        "shares": -34,
        "amount": -27072.5
      },
      {
        "symbol": "ADANIPOWER",
        "shares": -69,
        "amount": -26178.6
      },
      {
        "symbol": "LUPIN",
        "shares": -22,
        "amount": -25315.4
      },
      {
        "symbol": "TATACOMM",
        "shares": -12,
        "amount": -23132.4
      },
      {
        "symbol": "CGPOWER",
        "shares": -52,
        "amount": -22682.399999999998
      },
      {
        "symbol": "VBL",
        "shares": -22,
        "amount": -20144.3
      },
      {
        "symbol": "TIINDIA",
        "shares": -6,
        "amount": -19914.6
      },
      {
        "symbol": "DEVYANI",
        "shares": -93,
        "amount": -19664.85
      },
      {
        "symbol": "LAURUSLABS",
        "shares": -49,
        "amount": -19646.55
      },
      {
        "symbol": "INDHOTEL",
        "shares": -44,
        "amount": -18332.6
      },
      {
        "symbol": "APOLLOTYRE",
        "shares": -43,
        "amount": -16185.199999999999
      },
      {
        "symbol": "DIVISLAB",
        "shares": -4,
        "amount": -15262.0
      },
      {
        "symbol": "ALKEM",
        "shares": -4,
        "amount": -14703.8
      },
      {
        "symbol": "TATAELXSI",
        "shares": -2,
        "amount": -14469.3
      },
      {
        "symbol": "FACT",
        "shares": -23,
        "amount": -13036.4
      },
      {
        "symbol": "BAJAJ-AUTO",
        "shares": 3,
        "amount": 15391.5
      },
      {
        "symbol": "HAVELLS",
        "shares": 11,
        "amount": 15741.55
      },
      {
        "symbol": "IPCALAB",
        "shares": 17,
        "amount": 15822.75
      },
      {
        "symbol": "BHARATFORG",
        "shares": 14,
        "amount": 15881.600000000002
      },
      {
        "symbol": "MAZDOCK",
        "shares": 7,
        "amount": 15890.0
      },
      {
        "symbol": "PAYTM",
        "shares": 18,
        "amount": 15932.699999999999
      },
      {
        "symbol": "CHOLAFIN",
        "shares": 13,
        "amount": 15952.3
      },
      {
        "symbol": "HDFCAMC",
        "shares": 6,
        "amount": 16356.300000000001
      },
      {
        "symbol": "BANDHANBNK",
        "shares": 66,
        "amount": 16457.1
      },
      {
        "symbol": "RVNL",
        "shares": 97,
        "amount": 16504.55
      },
      {
        "symbol": "ZOMATO",
        "shares": 161,
        "amount": 16574.95
      },
      {
        "symbol": "YESBANK",
        "shares": 910,
        "amount": 16653.0
      },
      {
        "symbol": "ICICIPRULI",
        "shares": 28,
        "amount": 16660.0
      },
      {
        "symbol": "IDEA",
        "shares": 1424,
        "amount": 16660.8
      }
    ],
    "capital_incurred": -69261.80000000003,
    "start_date": "2023-05-09",
    "end_date": "2023-09-15"
  }
}